<?xml version="1.0" encoding="UTF-8"?>
<objects serializationModel="Studio.02.02.00">
	<object class="AudioFile" id="{be60e45f-cd97-45eb-b524-e24f0c9daeb7}">
		<property name="assetPath">
			<value>Provided Assets [LH]/Footsteps/Footstep2.wav</value>
		</property>
		<property name="frequencyInKHz">
			<value>44.0999985</value>
		</property>
		<property name="channelCount">
			<value>2</value>
		</property>
		<property name="length">
			<value>0.97916099773242626</value>
		</property>
		<relationship name="masterAssetFolder">
			<destination>{42cba907-803a-4325-9dc1-71b9a5046086}</destination>
		</relationship>
	</object>
</objects>
